AUTHORS
CHANGELOG.rst
LICENSE
MANIFEST.in
README.rst
setup.py
pg_fabrep/__init__.py
pg_fabrep/example_fabfile.py
pg_fabrep/tasks.py
pg_fabrep.egg-info/PKG-INFO
pg_fabrep.egg-info/SOURCES.txt
pg_fabrep.egg-info/dependency_links.txt
pg_fabrep.egg-info/namespace_packages.txt
pg_fabrep.egg-info/not-zip-safe
pg_fabrep.egg-info/requires.txt
pg_fabrep.egg-info/top_level.txt
pg_fabrep/conf/postgres/pg_hba.conf
pg_fabrep/conf/postgres/postgresql.conf
pg_fabrep/conf/repmgr/recovery.conf
pg_fabrep/conf/repmgr/repmgr.conf
pg_fabrep/deb/.empty
pg_fabrep/deb/postgresql-repmgr-9.0_1.0.0.deb
pg_fabrep/deb/postgresql-repmgr-9.1_1.0.0.deb