Metadata-Version: 1.0
Name: pg-fabrep
Version: 0.0.1
Summary: Postgresql Streaming Replication with Fabric and Repmgr
Home-page: https://bitbucket.org/DNX/pg_fabrep/
Author: Darii Denis
Author-email: denis.darii@gmail.com
License: BSD License
Download-URL: http://bitbucket.org/DNX/pg_fabrep/downloads
Keywords: postgres streaming replication fabric repmgr
Platform: UNKNOWN
Classifier: Development Status :: 3 - Alpha
Classifier: Environment :: Console
Classifier: Intended Audience :: Developers
Classifier: Intended Audience :: System Administrators
Classifier: Operating System :: MacOS :: MacOS X
Classifier: Operating System :: Unix
Classifier: Operating System :: POSIX
Classifier: Programming Language :: Python
Classifier: Programming Language :: Python :: 2.5
Classifier: Programming Language :: Python :: 2.6
Classifier: Topic :: Software Development
Classifier: Topic :: Software Development :: Build Tools
Classifier: Topic :: Software Development :: Libraries
Classifier: Topic :: Software Development :: Libraries :: Python Modules
Classifier: Topic :: System :: Clustering
Classifier: Topic :: System :: Software Distribution
Classifier: Topic :: System :: Systems Administration
